{
  "accentColor": "{{appsmith.theme.colors.primaryColor}}",
  "animateLoading": true,
  "backgroundColor": "#FFFFFF",
  "borderColor": "#E0DEDE",
  "borderRadius": "{{appsmith.theme.borderRadius.appBorderRadius}}",
  "borderWidth": 1,
  "bottomRow": 55,
  "boxShadow": "{{appsmith.theme.boxShadow.appBoxShadow}}",
  "children": [
    {
      "borderRadius": "{{appsmith.theme.borderRadius.appBorderRadius}}",
      "bottomRow": 450,
      "boxShadow": "{{appsmith.theme.boxShadow.appBoxShadow}}",
      "canExtend": false,
      "containerStyle": "none",
      "detachFromLayout": true,
      "dynamicBindingPathList": [
        {
          "key": "borderRadius"
        },
        {
          "key": "boxShadow"
        }
      ],
      "dynamicHeight": "AUTO_HEIGHT",
      "dynamicTriggerPathList": [],
      "flexLayers": [],
      "isLoading": false,
      "isVisible": true,
      "key": "hdek6soxbi",
      "leftColumn": 0,
      "maxDynamicHeight": 9000,
      "minDynamicHeight": 4,
      "minHeight": 490,
      "minWidth": 450,
      "mobileBottomRow": 491,
      "mobileLeftColumn": 0,
      "mobileRightColumn": 1248,
      "mobileTopRow": 1,
      "needsErrorInfo": false,
      "parentColumnSpace": 1,
      "parentId": "ifcrok1um6",
      "parentRowSpace": 1,
      "renderMode": "CANVAS",
      "responsiveBehavior": "fill",
      "rightColumn": 1248,
      "tabId": "tabl5ylaxrj14",
      "tabName": "Please Confirm",
      "topRow": 1,
      "type": "CANVAS_WIDGET",
      "version": 1,
      "widgetId": "l5swv7jptk",
      "widgetName": "Canvas6"
    }
  ],
  "defaultTab": "{{appsmith.store.AppSettings.Authorization_Tab_Default}}",
  "dynamicBindingPathList": [
    {
      "key": "accentColor"
    },
    {
      "key": "borderRadius"
    },
    {
      "key": "boxShadow"
    },
    {
      "key": "tabsObj.tabl5ylaxrj14.isVisible"
    },
    {
      "key": "defaultTab"
    }
  ],
  "dynamicHeight": "FIXED",
  "dynamicPropertyPathList": [
    {
      "key": "tabsObj.tabl5ylaxrj14.isVisible"
    },
    {
      "key": "tabsObj.tab2.isVisible"
    },
    {
      "key": "tabsObj.tab1.isVisible"
    },
    {
      "key": "tabsObj.tabzbyf03zr82.isVisible"
    }
  ],
  "dynamicTriggerPathList": [],
  "flexVerticalAlignment": "stretch",
  "isCanvas": true,
  "isLoading": false,
  "isVisible": true,
  "key": "a1lvb5tevz",
  "leftColumn": 0,
  "maxDynamicHeight": 9000,
  "minDynamicHeight": 15,
  "minWidth": 450,
  "mobileBottomRow": 27,
  "mobileLeftColumn": 1,
  "mobileRightColumn": 25,
  "mobileTopRow": 12,
  "needsErrorInfo": false,
  "parentColumnSpace": 19.5,
  "parentId": "0",
  "parentRowSpace": 10,
  "renderMode": "CANVAS",
  "responsiveBehavior": "fill",
  "rightColumn": 64,
  "shouldScrollContents": true,
  "shouldShowTabs": true,
  "tabsObj": {
    "tabl5ylaxrj14": {
      "id": "tabl5ylaxrj14",
      "index": 0,
      "isDuplicateLabel": false,
      "isVisible": "{{appsmith.store.AppSettings.Authorization_Tab_Logout_IsVisible}}",
      "label": "Please Confirm",
      "widgetId": "l5swv7jptk"
    }
  },
  "topRow": 6,
  "type": "TABS_WIDGET",
  "version": 3,
  "widgetId": "ifcrok1um6",
  "widgetName": "tab_LoginRegister"
}